Workbook

Sheet Setup & price
A1: Product/service | B1: Type | C1: Price
A2: Solar panels | C2: 47400
A3: Inverter | C3: 20625
A4: Battery | C4: 20925
A5: Mounting kit | C5: 11680
A6: Setup & installation | C6: 49335
A7: Interest rate for loan | C7: 8000
A8: Total | C8: =SUM(C2:C7) -> 157965

Sheet All of 2025 Payback time
B1: PRODUCTION (kWh) | F1: CONSUMPTION (kWh) | M1: COST | U1: BETTER USE OF SETUP V1 | Y1: BETTER USE OF SETUP V2
B2: Production | C2: Electricity used directly | D2: Sent to grid (Sold) | E2: Sent to battery | F2: Consumption | G2: Used by battery | H2: Total electricity used from own production | I2: Used directly from grid (ie not through battery) | J2: Used from grid | K2: EV charged | L2: Usage without EV | M2: kr/kWh | N2: Paid | Q2: Saved | R2: Earnings from the grid | S2: Saved | U2: Potential kWh avoided from grid | V2: Assumption for month | W2: Potential savings | Y2: Potential savings per kWh (assumption: half the average price) | Z2: Amount of kWh to charge through arbitrage | AA2: Saved
A3: January | B3: 214 | C3: 198 | D3: 16 | E3: 0 | F3: 1660 | G3: 428 | H3: =C3+E3 -> 198 | I3: 1030 | J3: 1478 | K3: 514 | L3: =F3-K3 -> 1146 | M3: 1.87 | N3: =J3*M3 -> 2763.86 | Q3: =(M3)*H3 -> 370.26 | R3: 22 | U3: =D3 -> 16 | V3: Could have used all we generated | W3: =U3*M3 -> 29.92 | Y3: =M3/2 -> 0.935 | Z3: =G3 -> 428 | AA3: =Y3*Z3 -> 400.18
A4: February | B4: 520 | C4: 15 | D4: 106 | E4: 398 | F4: 1500 | G4: 385 | H4: =C4+E4 -> 413 | I4: 1100 | J4: 1100 | K4: 450 | L4: =F4-K4 -> 1050 | M4: 1.87 | N4: =J4*M4 -> 2057 | Q4: =(M4)*H4 -> 772.31 | R4: 20 | U4: =D4 -> 106 | V4: Could have used all we generated | W4: =U4*M4 -> 198.22 | Y4: =M4/2 -> 0.935 | Z4: =G4 -> 385 | AA4: =Y4*Z4 -> 359.975
A5: March | B5: 1480 | C5: 417 | D5: 669 | E5: 398 | F5: 1350 | G5: 382 | H5: =C5+E5 -> 815 | I5: 559 | J5: 563 | K5: 385 | L5: =F5-K5 -> 965 | M5: =(N5-(7+19+24))/J5 -> 1.4458259 | N5: 864 | Q5: =(M5)*H5 -> 1178.3481 | R5: 191 | U5: =D5*0.5 -> 334.5 | V5: Could have used 50% of what we sent to grid | W5: =U5*M5 -> 483.62877 | Y5: =M5/2 -> 0.72291297 | Z5: =G5 -> 382 | AA5: =Y5*Z5 -> 276.15275
A6: April | B6: 2040 | C6: 747 | D6: 975 | E6: 324 | F6: 1300 | G6: 315 | H6: =C6+E6 -> 1071 | I6: 238 | J6: 242 | K6: 456 | L6: =F6-K6 -> 844 | M6: =(N6-(7+19+24))/J6 -> 1.3347107 | N6: 373 | Q6: =(M6)*H6 -> 1429.4752 | R6: 187 | U6: =J6 -> 242 | V6: Would have been self supplying | W6: =U6*M6 -> 323 | Y6: =M6/2 -> 0.66735537 | Z6: 0 | AA6: =Y6*Z6 -> 0
A7: May | B7: 2330 | C7: 513 | D7: 1550 | E7: 264 | F7: 857 | G7: 234 | H7: =C7+E7 -> 777 | I7: 134 | J7: 150 | K7: 245 | L7: =F7-K7 -> 612 | M7: =(N7-(7+19+24))/J7 -> 1.7066667 | N7: 306 | Q7: =(M7)*H7 -> 1326.08 | R7: 268 | U7: =J7 -> 150 | V7: Would have been self supplying | W7: =U7*M7 -> 256 | Y7: =M7/2 -> 0.85333333 | Z7: 0 | AA7: =Y7*Z7 -> 0
A8: June | B8: 2380 | C8: 613 | D8: 1510 | E8: 257 | F8: 1000 | G8: 250 | H8: =C8+E8 -> 870 | I8: 143 | J8: 150 | K8: 339 | L8: =F8-K8 -> 661 | M8: =(N8-(7+19+24))/J8 -> 1.84 | N8: 326 | Q8: =(M8)*H8 -> 1600.8 | R8: 124 | U8: =J8 -> 150 | V8: Would have been self supplying | W8: =U8*M8 -> 276 | Y8: =M8/2 -> 0.92 | Z8: 0 | AA8: =Y8*Z8 -> 0
A9: July | B9: 2160 | C9: 552 | D9: 1360 | E9: 250 | F9: 926 | G9: 239 | H9: =C9+E9 -> 802 | I9: 135 | J9: 140 | K9: 299 | L9: =F9-K9 -> 627 | M9: =(N9-(7+19+24))/J9 -> 1.8571429 | N9: 310 | Q9: =(M9)*H9 -> 1489.4286 | R9: 480 | U9: =J9 -> 140 | V9: Would have been self supplying | W9: =U9*M9 -> 260 | Y9: =M9/2 -> 0.92857143 | Z9: 0 | AA9: =Y9*Z9 -> 0
A10: August | B10: 2150 | C10: 556 | D10: 1330 | E10: 261 | F10: 1080 | G10: 316 | H10: =C10+E10 -> 817 | I10: 163 | J10: 251 | K10: 290 | L10: =F10-K10 -> 790 | M10: =(N10-(7+19+24))/J10 -> 1.7171315 | N10: 481 | Q10: =(M10)*H10 -> 1402.8964 | R10: 263 | U10: =J10 -> 251 | V10: Would have been self supplying | W10: =U10*M10 -> 431 | Y10: =M10/2 -> 0.85856574 | Z10: 0 | AA10: =Y10*Z10 -> 0
A11: September | B11: 1630 | C11: 439 | D11: 940 | E11: 252 | F11: 1030 | G11: 328 | H11: =C11+E11 -> 691 | I11: 267 | J11: 363 | K11: 351 | L11: =F11-K11 -> 679 | M11: =(N11-(7+19+24))/J11 -> 2.2809917 | N11: =635+243 -> 878 | Q11: =(M11)*H11 -> 1576.1653 | R11: 276 | U11: =J11 -> 363 | V11: Would have been self supplying | W11: =U11*M11 -> 828 | Y11: =M11/2 -> 1.1404959 | Z11: =G11 -> 328 | AA11: =Y11*Z11 -> 374.08264
A12: October | B12: 783 | C12: 275 | D12: 325 | E12: 183 | F12: 1500 | G12: 402 | H12: =C12+E12 -> 458 | I12: 824 | J12: 1063 | K12: 486 | L12: =F12-K12 -> 1014 | M12: =(N12-(7+19+24))/J12 -> 2.1004327 | N12: 2282.76 | Q12: =(M12)*H12 -> 961.99819 | R12: 163 | U12: =D12 -> 325 | V12: Could have used all we generated | W12: =U12*M12 -> 682.64064 | Y12: =M12/2 -> 1.0502164 | Z12: =G12 -> 402 | AA12: =Y12*Z12 -> 422.18698
A13: November | B13: 364 | C13: 187 | D13: 70 | E13: 107 | F13: 1700 | G13: 374 | H13: =C13+E13 -> 294 | I13: 1140 | J13: 1421 | K13: 429 | L13: =F13-K13 -> 1271 | M13: =(N13-(7+19+24))/J13 -> 1.4789303 | N13: 2151.56 | Q13: =(M13)*H13 -> 434.80552 | U13: =D13 -> 70 | V13: Could have used all we generated | W13: =U13*M13 -> 103.52512 | Y13: =M13/2 -> 0.73946517 | Z13: =G13 -> 374 | AA13: =Y13*Z13 -> 276.55997
A14: December | B14: 225 | C14: 113 | D14: 26 | E14: 86 | F14: 1750 | G14: 366 | H14: =C14+E14 -> 199 | I14: 1270 | J14: 1555 | K14: 423 | L14: =F14-K14 -> 1327 | M14: =(N14-(7+19+24))/J14 -> 1.3514855 | N14: 2151.56 | Q14: =(M14)*H14 -> 268.94562 | U14: =D14 -> 26 | V14: Could have used all we generated | W14: =U14*M14 -> 35.138624 | Y14: =M14/2 -> 0.67574277 | Z14: =G14 -> 366 | AA14: =Y14*Z14 -> 247.32185
A17: Total | B17: =SUM(B3:B14) -> 16276 | C17: =SUM(C3:C14) -> 4625 | D17: =SUM(D3:D14) -> 8877 | E17: =SUM(E3:E14) -> 2780 | F17: =SUM(F3:F14) -> 15653 | G17: =SUM(G3:G14) -> 4019 | H17: =SUM(H3:H14) -> 7405 | I17: =SUM(I3:I14) -> 7003 | ... L17: =SUM(L3:L14) -> 10986 | N17: =SUM(N3:N14) -> 14944.74 | Q17: =SUM(Q3:Q14) -> 12811.513 | R17: =SUM(R3:R14) -> 1994 | S17: =Q17+R17 -> 14805.513 | U17: =SUM(U3:U6) -> 698.5 | W17: =SUM(W3:W6) -> 1034.7688 | AA17: =SUM(AA3:AA14) -> 2356.4592
I18: The difference may be the battery that has taken from the grid
A20: Total price for setup | B20: ='Setup & price'!C8 -> 157965
A21: Payback time | B21: =B20/S17 -> 10.669337
A22: With improved use of setup | B22: =B20/(S17+W17) -> 9.9723605
A23: With better energy arbitrage | B23: =B20/(S17+W17+AA17) -> 8.6809501

Sheet 2025 CO2 savings
B1: OWN PRODUCTION | F1: OWN CONSUMPTION | T1: GAS VS HEATPUMP
B2: Production | C2: Used directly | D2: Sent to grid (Sold) | E2: Sent to battery | F2: Consumption | G2: Used by battery | H2: Total electricity used from own production | I2: Used from grid | J2: Non-EV kWh consumptiom | L2: Avr CO2/kWh | M2: Kg CO2 saved ent production | N2: CO2 saved in own use | O2: CO2 saved in sent to grid | Q2: Emissions from grid | R2: Emissions if all was from grid | T2: Heat pump active | U2: Estimated kWh use | V2: Estimated kWh use | W2: Estimated CO2 from heat pump | X2: Gas boiler kWh use
A3: January | B3: 214 | C3: 198 | D3: 16 | E3: 0 | F3: 1660 | G3: 428 | H3: =C3+E3 -> 198 | I3: 1478 | J3: ='All of 2025 Payback time'!L3 -> 1146 | L3: 186 | M3: =(B3*L3)/1000 -> 39.804 | N3: =(H3*L3)/1000 -> 36.828 | O3: =(D3*L3)/1000 -> 2.976 | Q3: =(L3*I3)/1000 -> 274.908 | R3: =(L3*F3)/1000 -> 308.76 | T3: x | U3: =J3-700 -> 446 | V3: 726 | W3: =(V3*L3)/1000 -> 135.036
A4: February | B4: 520 | C4: 15 | D4: 106 | E4: 398 | F4: 1500 | G4: 385 | H4: =C4+E4 -> 413 | I4: 1100 | J4: ='All of 2025 Payback time'!L4 -> 1050 | L4: 243 | M4: =(B4*L4)/1000 -> 126.36 | N4: =(H4*L4)/1000 -> 100.359 | O4: =(D4*L4)/1000 -> 25.758 | Q4: =(L4*I4)/1000 -> 267.3 | R4: =(L4*F4)/1000 -> 364.5 | T4: x | U4: =J4-700 -> 350 | V4: 659 | W4: =(V4*L4)/1000 -> 160.137
A5: March | B5: 1480 | C5: 417 | D5: 669 | E5: 398 | F5: 1350 | G5: 382 | H5: =C5+E5 -> 815 | I5: 563 | J5: ='All of 2025 Payback time'!L5 -> 965 | L5: 180 | M5: =(B5*L5)/1000 -> 266.4 | N5: =(H5*L5)/1000 -> 146.7 | O5: =(D5*L5)/1000 -> 120.42 | Q5: =(L5*I5)/1000 -> 101.34 | R5: =(L5*F5)/1000 -> 243 | T5: x | U5: =J5-700 -> 265 | V5: 646 | W5: =(V5*L5)/1000 -> 116.28
A6: April | B6: 2040 | C6: 747 | D6: 975 | E6: 324 | F6: 1300 | G6: 315 | H6: =C6+E6 -> 1071 | I6: 242 | J6: ='All of 2025 Payback time'!L6 -> 844 | L6: 203 | M6: =(B6*L6)/1000 -> 414.12 | N6: =(H6*L6)/1000 -> 217.413 | O6: =(D6*L6)/1000 -> 197.925 | Q6: =(L6*I6)/1000 -> 49.126 | R6: =(L6*F6)/1000 -> 263.9 | T6: x | U6: =J6-700 -> 144 | V6: 464 | W6: =(V6*L6)/1000 -> 94.192
A7: May | B7: 2330 | C7: 513 | D7: 1550 | E7: 264 | F7: 857 | G7: 234 | H7: =C7+E7 -> 777 | I7: 150 | J7: ='All of 2025 Payback time'!L7 -> 612 | L7: 116 | M7: =(B7*L7)/1000 -> 270.28 | N7: =(H7*L7)/1000 -> 90.132 | O7: =(D7*L7)/1000 -> 179.8 | Q7: =(L7*I7)/1000 -> 17.4 | R7: =(L7*F7)/1000 -> 99.412 | W7: =(V7*L7)/1000 -> 0
A8: June | B8: 2380 | C8: 613 | D8: 1510 | E8: 257 | F8: 1000 | G8: 250 | H8: =C8+E8 -> 870 | I8: 150 | J8: ='All of 2025 Payback time'!L8 -> 661 | L8: 94 | M8: =(B8*L8)/1000 -> 223.72 | N8: =(H8*L8)/1000 -> 81.78 | O8: =(D8*L8)/1000 -> 141.94 | Q8: =(L8*I8)/1000 -> 14.1 | R8: =(L8*F8)/1000 -> 94 | W8: =(V8*L8)/1000 -> 0
A9: July | B9: 2160 | C9: 552 | D9: 1360 | E9: 250 | F9: 926 | G9: 239 | H9: =C9+E9 -> 802 | I9: 140 | J9: ='All of 2025 Payback time'!L9 -> 627 | L9: 123 | M9: =(B9*L9)/1000 -> 265.68 | N9: =(H9*L9)/1000 -> 98.646 | O9: =(D9*L9)/1000 -> 167.28 | Q9: =(L9*I9)/1000 -> 17.22 | R9: =(L9*F9)/1000 -> 113.898 | W9: =(V9*L9)/1000 -> 0
A10: August | B10: 2150 | C10: 556 | D10: 1330 | E10: 261 | F10: 1080 | G10: 316 | H10: =C10+E10 -> 817 | I10: 251 | J10: ='All of 2025 Payback time'!L10 -> 790 | L10: 117 | M10: =(B10*L10)/1000 -> 251.55 | N10: =(H10*L10)/1000 -> 95.589 | O10: =(D10*L10)/1000 -> 155.61 | Q10: =(L10*I10)/1000 -> 29.367 | R10: =(L10*F10)/1000 -> 126.36 | W10: =(V10*L10)/1000 -> 0
A11: September | B11: 1630 | C11: 439 | D11: 940 | E11: 252 | F11: 1030 | G11: 328 | H11: =C11+E11 -> 691 | I11: 363 | J11: ='All of 2025 Payback time'!L11 -> 679 | L11: 98 | M11: =(B11*L11)/1000 -> 159.74 | N11: =(H11*L11)/1000 -> 67.718 | O11: =(D11*L11)/1000 -> 92.12 | Q11: =(L11*I11)/1000 -> 35.574 | R11: =(L11*F11)/1000 -> 100.94 | W11: =(V11*L11)/1000 -> 0
A12: October | B12: 783 | C12: 275 | D12: 325 | E12: 183 | F12: 1500 | G12: 402 | H12: =C12+E12 -> 458 | I12: 1063 | J12: ='All of 2025 Payback time'!L12 -> 1014 | L12: 128 | M12: =(B12*L12)/1000 -> 100.224 | N12: =(H12*L12)/1000 -> 58.624 | O12: =(D12*L12)/1000 -> 41.6 | Q12: =(L12*I12)/1000 -> 136.064 | R12: =(L12*F12)/1000 -> 192 | T12: x | U12: =J12-700 -> 314 | V12: 353 | W12: =(V12*L12)/1000 -> 45.184
A13: November | B13: 364 | C13: 187 | D13: 70 | E13: 107 | F13: 1700 | G13: 374 | H13: =C13+E13 -> 294 | I13: 1421 | J13: ='All of 2025 Payback time'!L13 -> 1271 | L13: 197 | M13: =(B13*L13)/1000 -> 71.708 | N13: =(H13*L13)/1000 -> 57.918 | O13: =(D13*L13)/1000 -> 13.79 | Q13: =(L13*I13)/1000 -> 279.937 | R13: =(L13*F13)/1000 -> 334.9 | T13: x | U13: =J13-700 -> 571 | V13: 498 | W13: =(V13*L13)/1000 -> 98.106
A14: December | B14: 225 | C14: 113 | D14: 26 | E14: 86 | F14: 1750 | G14: 366 | H14: =C14+E14 -> 199 | I14: 1555 | J14: ='All of 2025 Payback time'!L14 -> 1327 | L14: 187 | M14: =(B14*L14)/1000 -> 42.075 | N14: =(H14*L14)/1000 -> 37.213 | O14: =(D14*L14)/1000 -> 4.862 | Q14: =(L14*I14)/1000 -> 290.785 | R14: =(L14*F14)/1000 -> 327.25 | T14: x | U14: =J14-700 -> 627 | V14: 668 | W14: =(V14*L14)/1000 -> 124.916
A16: Total | B16: =SUM(B3:B14) -> 16276 | C16: =SUM(C3:C14) -> 4625 | D16: =SUM(D3:D14) -> 8877 | E16: =SUM(E3:E14) -> 2780 | F16: =SUM(F3:F14) -> 15653 | G16: =SUM(G3:G14) -> 4019 | H16: =SUM(H3:H14) -> 7405 | I16: =SUM(I3:I6) -> 3383 | J16: =SUM(J3:J6) -> 4005 | L16: =AVERAGE(L3:L14) -> 156 | M16: =SUM(M3:M14) -> 2231.661 | N16: =SUM(N3:N14) -> 1088.92 | O16: =SUM(O3:O14) -> 1144.081 | Q16: =SUM(Q3:Q14) -> 1513.121 | R16: =SUM(R3:R14) -> 2568.92 | V16: =SUM(V3:V14) -> 4014 | W16: =SUM(W3:W14) -> 773.851
R17: =R16-Q16 -> 1055.799 | X17: 3000
L18: https://www.nowtricity.com/country/denmark/
A26: Tilbagebetalingstid ved optimalt brug af setup
A27: If we were able to use all electricity produced | B27: =(B15-G15)/10 -> 0
A28: Monthly savings | B28: =B27*#REF! -> #REF!

Sheet 2025 without elafgift
B1: Production | C1: Consumption | D1: Electricity used directly | E1: Grid (Sold) | F1: Sent to battery | G1: Used by battery | H1: Total electricity used from own production | I1: Taken from grid (Solarman - not accurate) | J1: Used from grid | K1: EV charged | L1: Price paid per kWh | M1: Paid | N1: NO ELAFGIFT NEW PRICE PR KWH | O1: PRICE | P1: Usage without EV | R1: Pris hvis ikke vi havde solceller | S1: Saved | T1: Indtjening fra elnettet | U1: Totalt sparet | V1: Reduktion i elafgift pr kWh | W1: I alt elafgift | X1: Solgt til elnettet | Y1: Hvis vi kunne have udnyttet kapaciteten bedre (brugt 40% af den strøm vi har solgt til elnettet og undgået at købe strøm på de tidspunkter) | Z1: Antagelse
A2: January | B2: 214 | C2: 1660 | D2: 198 | E2: 16 | F2: 0 | G2: 428 | H2: =D2+F2 -> 198 | I2: 1030 | J2: 1478 | K2: 514 | L2: 1.87 | M2: =J2*L2 -> 2763.86 | N2: =L2-V2 -> 1.05 | O2: =N2*J2 -> 1551.9 | P2: =C2-K2 -> 1146 | S2: =(N2+0.25)*H2 -> 257.4 | T2: 22 | V2: 0.82 | Y2: =(E2*#REF!)+(0.5*J2) -> #REF! | Z2: Vi kunne have sparet 0,5 kr. pr importeret kWh
A3: February | B3: 520 | C3: 1500 | D3: 15 | E3: 106 | F3: 398 | G3: 385 | H3: =D3+F3 -> 413 | I3: 1100 | J3: 1100 | K3: 450 | L3: 1.87 | M3: =J3*L3 -> 2057 | N3: =L3-V3 -> 1.05 | O3: =N3*J3 -> 1155 | P3: =C3-K3 -> 1050 | S3: =(N3+0.25)*H3 -> 536.9 | T3: 20 | V3: 0.82 | Y3: =(E3*#REF!)+(0.5*J3) -> #REF! | Z3: Vi kunne have sparet 0,5 kr. pr importeret kWh
A4: March | B4: 1480 | C4: 1350 | D4: 417 | E4: 669 | F4: 398 | G4: 382 | H4: =D4+F4 -> 815 | I4: 559 | J4: 563 | K4: 385 | L4: =(M4-(7+19+24))/J4 -> 1.4458259 | M4: 864 | N4: =L4-V4 -> 0.62582593 | O4: =N4*J4 -> 352.34 | P4: =C4-K4 -> 965 | S4: =(N4+0.25)*H4 -> 713.79814 | T4: 191 | V4: 0.82
A5: April | B5: 2040 | C5: 1300 | D5: 747 | E5: 975 | F5: 324 | G5: 315 | H5: =D5+F5 -> 1071 | I5: 238 | J5: 242 | K5: 456 | L5: =(M5-(7+19+24))/J5 -> 1.3347107 | M5: 373 | N5: =L5-V5 -> 0.51471074 | O5: =N5*J5 -> 124.56 | P5: =C5-K5 -> 844 | S5: =(N5+0.25)*H5 -> 819.00521 | T5: 187 | V5: 0.82
A6: May | B6: 2330 | C6: 857 | D6: 513 | E6: 1550 | F6: 264 | G6: 234 | H6: =D6+F6 -> 777 | I6: 134 | J6: 150 | K6: 245 | L6: =(M6-(7+19+24))/J6 -> 1.7066667 | M6: 306 | N6: =L6-V6 -> 0.88666667 | O6: =N6*J6 -> 133 | P6: =C6-K6 -> 612 | S6: =(N6+0.25)*H6 -> 883.19 | T6: 268 | V6: 0.82 | Y6: =J6*1*#REF!-(T6/2) -> #REF! | Z6: Vi kunne have undgået al import af strøm (men til gengæld også kun eksporteret halvt så meget)
A7: June | B7: 2380 | C7: 1000 | D7: 613 | E7: 1510 | F7: 257 | G7: 250 | H7: =D7+F7 -> 870 | I7: 143 | J7: 150 | K7: 339 | L7: =(M7-(7+19+24))/J7 -> 1.84 | M7: 326 | N7: =L7-V7 -> 1.02 | O7: =N7*J7 -> 153 | P7: =C7-K7 -> 661 | S7: =(N7+0.25)*H7 -> 1104.9 | T7: 124 | V7: 0.82 | Y7: =J7*1*#REF!-(T7/2) -> #REF! | Z7: Vi kunne have undgået al import af strøm (men til gengæld også kun eksporteret halvt så meget)
A8: July | B8: 2160 | C8: 926 | D8: 552 | E8: 1360 | F8: 250 | G8: 239 | H8: =D8+F8 -> 802 | I8: 135 | J8: 140 | K8: 299 | L8: =(M8-(7+19+24))/J8 -> 1.8571429 | M8: 310 | N8: =L8-V8 -> 1.0371429 | O8: =N8*J8 -> 145.2 | P8: =C8-K8 -> 627 | S8: =(N8+0.25)*H8 -> 1032.2886 | T8: 480 | V8: 0.82 | Y8: =J8*1*#REF!-(T8/2) -> #REF! | Z8: Vi kunne have undgået al import af strøm (men til gengæld også kun eksporteret halvt så meget)
A9: August | B9: 2150 | C9: 1080 | D9: 556 | E9: 1330 | F9: 261 | G9: 316 | H9: =D9+F9 -> 817 | I9: 163 | J9: 251 | K9: 290 | L9: =(M9-(7+19+24))/J9 -> 1.7171315 | M9: 481 | N9: =L9-V9 -> 0.89713147 | O9: =N9*J9 -> 225.18 | P9: =C9-K9 -> 790 | S9: =(N9+0.25)*H9 -> 937.20641 | T9: 263 | V9: 0.82 | Y9: =J9*1*#REF!-(T9/2) -> #REF! | Z9: Vi kunne have undgået al import af strøm (men til gengæld også kun eksporteret halvt så meget)
A10: September | B10: 1630 | C10: 1030 | D10: 439 | E10: 940 | F10: 252 | G10: 328 | H10: =D10+F10 -> 691 | I10: 267 | J10: 363 | K10: 351 | L10: =(M10-(7+19+24))/J10 -> 2.2809917 | M10: =635+243 -> 878 | N10: =L10-V10 -> 1.4609917 | O10: =N10*J10 -> 530.34 | P10: =C10-K10 -> 679 | S10: =(N10+0.25)*H10 -> 1182.2953 | T10: 276 | V10: 0.82 | Y10: =J10*0.7*#REF! -> #REF! | Z10: Vi kunne have undgået 70% + sparet resten ved at lade batteriet når strømmen var billig
A11: October | B11: 783 | C11: 1500 | D11: 275 | E11: 325 | F11: 183 | G11: 402 | H11: =D11+F11 -> 458 | I11: 824 | J11: 1063 | K11: 486 | L11: =(M11-(7+19+24))/J11 -> 2.1004327 | M11: 2282.76 | N11: =L11-V11 -> 1.2804327 | O11: =N11*J11 -> 1361.1 | P11: =C11-K11 -> 1014 | S11: =(N11+0.25)*H11 -> 700.93819 | T11: 163 | V11: 0.82 | Y11: =J11*0.5*#REF! -> #REF! | Z11: Vi kunne have undgået 50% + sparet resten ved at lade batteriet når strømmen var billig
A12: November | B12: 364 | C12: 1700 | D12: 187 | E12: 70 | F12: 107 | G12: 374 | H12: =D12+F12 -> 294 | I12: 1140 | J12: 1421 | K12: 429 | L12: =(M12-(7+19+24))/J12 -> 1.4789303 | M12: 2151.56 | N12: =L12-V12 -> 0.65893033 | O12: =N12*J12 -> 936.34 | P12: =C12-K12 -> 1271 | S12: =(N12+0.25)*H12 -> 267.22552 | V12: 0.82 | Y12: =(E12*#REF!)+(0.5*J12) -> #REF! | Z12: Vi kunne have sparet 0,5 kr. pr importeret kWh
A13: December | B13: 225 | C13: 1750 | D13: 113 | E13: 26 | F13: 86 | G13: 366 | H13: =D13+F13 -> 199 | I13: 1270 | J13: 1555 | K13: 423 | L13: =(M13-(7+19+24))/J13 -> 1.3514855 | M13: 2151.56 | N13: =L13-V13 -> 0.53148553 | O13: =N13*J13 -> 826.46 | P13: =C13-K13 -> 1327 | S13: =(N13+0.25)*H13 -> 155.51562 | V13: 0.82 | Y13: =(E13*#REF!)+(0.5*J13) -> #REF! | Z13: Vi kunne have sparet 0,5 kr. pr importeret kWh
A16: Total | B16: =SUM(B2:B13) -> 16276 | C16: =SUM(C2:C13) -> 15653 | D16: =SUM(D2:D13) -> 4625 | E16: =SUM(E2:E13) -> 8877 | F16: =SUM(F2:F13) -> 2780 | G16: =SUM(G2:G13) -> 4019 | H16: =SUM(H2:H13) -> 7405 | I16: =SUM(I2:I5) -> 2927 | J16: =SUM(J2:J5) -> 3383 | K16: =SUM(K2:K5) -> 1805 | M16: =SUM(M2:M13) -> 14944.74 | O16: =SUM(O2:O5) -> 3183.8 | P16: =SUM(P2:P5) -> 4005 | S16: =SUM(S2:S13) -> 8590.6629 | T16: =SUM(T2:T13) -> 1994 | U16: =S16+T16 -> 10584.663 | Y16: =SUM(Y2:Y5) -> #REF!
B17: 11000 | C17: 14500 | H17: Average | J17: kWh | K17: kWh | L17: =AVERAGE(L2:L3) -> 1.87 | M17: =M16/9 -> 1660.5267 | P17: kWh
S18: ASSUMPTION: We would have paid approx 25 øre more per kWh due to not being able to spend electricity from the battery in high demand times
A19: Total price for setup | B19: 155000
A20: Payback time | B20: =B19/U16 -> 14.64383
A26: Tilbagebetalingstid ved optimalt brug af setup
A27: If we were able to use all electricity produced | B27: =(B15-G15)/10 -> 0
A28: Monthly savings | B28: =B27*#REF! -> #REF!

Sheet Chart1 Monthly Production vs. C
A3: Month | B3: Production | C3: Consumption
A4: January | B4: 214 | C4: 1660
A5: February | B5: 520 | C5: 1500
A6: March | B6: 1480 | C6: 1350
A7: April | B7: 2040 | C7: 1300
A8: May | B8: 2330 | C8: 857
A9: June | B9: 2380 | C9: 1000
A10: July | B10: 2160 | C10: 926
A11: August | B11: 2150 | C11: 1080
A12: September | B12: 1630 | C12: 1030
A13: October | B13: 783 | C13: 1500
A14: November | B14: 364 | C14: 1700
A15: December | B15: 225 | C15: 1750

Sheet (OLD)
B2: Production | C2: Sold | D2: Consumption | E2: Electricity used directly | F2: Battery | G2: Total electricity used from own production | H2: Taken from grid (Solarman - not accurate) | I2: Electricity from grid | J2: Difference SM/Watts | K2: EV charged | L2: Average market price electricity | M2: Acutal price | N2: Paid | O2: Reel pris b.energy | P2: Usage without EV | Q2: Saved | R2: Indtjening fra elnettet | S2: Totalt sparet | U2: Pris hvis ikke vi havde solceller | V2: Solgt til elnettet | W2: Hvis vi kunne have udnyttet kapaciteten bedre (brugt 40% af den strøm vi har solgt til elnettet og undgået at købe strøm på de tidspunkter) | X2: Antagelse
A3: May | B3: 823 | C3: 1.4 | D3: 1010 | E3: 577 | F3: 245 | G3: =E3+F3 -> 822 | H3: 193 | I3: 199 | J3: =I3-H3 -> 6 | K3: =0.8*363 -> 290.4 | L3: 2.48 | M3: 2.6 | N3: =I3*M3 -> 517.4 | P3: =D3-K3 -> 719.6 | Q3: =L3*G3 -> 2038.56 | R3: 250 | W3: =I3*1*L3-(R3/2) -> 368.52 | X3: Vi kunne have undgået al import af strøm (men til gengæld også kun eksporteret halvt så meget)
A4: June | B4: 757 | C4: 0.8 | D4: 940 | E4: 530 | F4: 226 | G4: =E4+F4 -> 756 | H4: 182 | I4: 187 | J4: =I4-H4 -> 5 | K4: =0.8*400 -> 320 | L4: 2.48 | M4: 2.6 | N4: =I4*M4 -> 486.2 | P4: =D4-K4 -> 620 | Q4: =L4*G4 -> 1874.88 | R4: 250 | W4: =I4*1*L4-(R4/2) -> 338.76 | X4: Vi kunne have undgået al import af strøm (men til gengæld også kun eksporteret halvt så meget)
A5: July | B5: 2000 | C5: 1300 | D5: 867 | E5: 485 | F5: 210 | G5: =E5+F5 -> 695 | H5: 172 | I5: 287 | J5: =I5-H5 -> 115 | K5: 325 | L5: 2.59 | M5: 2.6 | N5: =I5*M5 -> 746.2 | P5: =D5-K5 -> 542 | Q5: =L5*G5 -> 1800.05 | R5: 223 | W5: =I5*1*L5-(R5/2) -> 631.83 | X5: Vi kunne have undgået al import af strøm (men til gengæld også kun eksporteret halvt så meget)
A6: August | B6: 2070 | C6: 1360 | D6: 1110 | E6: 484 | F6: 224 | G6: =E6+F6 -> 708 | H6: 403 | I6: 407 | J6: =I6-H6 -> 4 | K6: =0.8*520 -> 416 | L6: 2.59 | M6: 2.46 | N6: =I6*M6 -> 1001.22 | P6: =D6-K6 -> 694 | Q6: =L6*G6 -> 1833.72 | R6: 401 | W6: =I6*1*L6-(R6/2) -> 853.63 | X6: Vi kunne have undgået al import af strøm (men til gengæld også kun eksporteret halvt så meget)
A7: September | B7: 1510 | C7: 869 | D7: 1100 | E7: 437 | F7: 203 | G7: =E7+F7 -> 640 | H7: 460 | I7: 463 | J7: =I7-H7 -> 3 | K7: =0.8*472 -> 377.6 | L7: 2.59 | M7: 2.4 | N7: =I7*M7 -> 1111.2 | P7: =D7-K7 -> 722.4 | Q7: =L7*G7 -> 1657.6 | R7: 228 | W7: =I7*0.7*L7 -> 839.419 | X7: Vi kunne have undgået 70% + sparet resten ved at lade batteriet når strømmen var billig
A8: October | B8: 938 | C8: 432 | D8: 1080 | E8: 408 | F8: 107 | G8: =E8+F8 -> 515 | H8: 573 | I8: 577 | J8: =I8-H8 -> 4 | K8: 311 | L8: 2.9 | M8: 2.5 | N8: =I8*M8 -> 1442.5 | P8: =D8-K8 -> 769 | Q8: =L8*G8 -> 1493.5 | R8: 159 | W8: =I8*0.5*L8 -> 836.65 | X8: Vi kunne have undgået 50% + sparet resten ved at lade batteriet når strømmen var billig
A9: November | B9: 272 | C9: 23 | D9: 1470 | E9: 249 | F9: 357 | G9: =E9+F9 -> 606 | H9: 866 | I9: 1250 | J9: =I9-H9 -> 384 | K9: 397 | L9: 2.9 | M9: 2.08 | N9: =I9*M9 -> 2600 | P9: =D9-K9 -> 1073 | Q9: =L9*G9 -> 1757.4 | R9: 60 | W9: =(C9*L9)+(0.5*I9) -> 691.7 | X9: Vi kunne have sparet 0,5 kr. pr importeret kWh
A10: December | B10: 156 | C10: 5 | D10: 1480 | E10: 152 | F10: 386 | G10: =E10+F10 -> 538 | H10: 950 | I10: 1350 | J10: =I10-H10 -> 400 | K10: =0.8*567 -> 453.6 | L10: 2.9 | M10: 2.02 | N10: =I10*M10 -> 2727 | P10: =D10-K10 -> 1026.4 | Q10: =L10*G10 -> 1560.2 | R10: 21 | W10: =(C10*L10)+(0.5*I10) -> 689.5 | X10: Vi kunne have sparet 0,5 kr. pr importeret kWh
A11: January | B11: 214 | C11: 16 | D11: 1660 | E11: 198 | F11: 429 | G11: =E11+F11 -> 627 | H11: 1030 | I11: 1478 | J11: =I11-H11 -> 448 | K11: 497 | L11: 2.8 | M11: 1.87 | N11: =I11*M11 -> 2763.86 | P11: =D11-K11 -> 1163 | Q11: =L11*G11 -> 1755.6 | R11: 22 | W11: =(C11*L11)+(0.5*I11) -> 783.8 | X11: Vi kunne have sparet 0,5 kr. pr importeret kWh
A12: February | B12: 520 | C12: 106 | D12: 1500 | E12: 15 | F12: 386 | G12: =E12+F12 -> 401 | H12: 1100 | I12: 1100 | J12: =I12-H12 -> 0 | K12: 364 | L12: 2.8 | M12: 1.87 | N12: =I12*M12 -> 2057 | P12: =D12-K12 -> 1136 | Q12: =L12*G12 -> 1122.8 | R12: 20 | W12: =(C12*L12)+(0.5*I12) -> 846.8 | X12: Vi kunne have sparet 0,5 kr. pr importeret kWh
A13: March | B13: 1480 | C13: 669 | D13: 1350 | E13: 417 | F13: 382 | G13: =E13+F13 -> 799 | H13: 559 | I13: 559 | K13: =467*0.8 -> 373.6 | L13: 2.8 | M13: 1.87 | N13: =I13*M13 -> 1045.33 | P13: =D13-K13 -> 976.4 | Q13: =L13*G13 -> 2237.2
A14: April
A17: Total | B17: =SUM(B3:B14) -> 10740 | C17: =SUM(C3:C14) -> 4782.2 | D17: =SUM(D3:D14) -> 13567 | E17: =SUM(E3:E14) -> 3952 | F17: =SUM(F3:F14) -> 3155 | G17: =SUM(G3:G14) -> 7107 | H17: =SUM(H3:H14) -> 6488 | I17: =SUM(I3:I14) -> 7857 | ... K17: =SUM(K3:K14) -> 4125.2 | N17: =SUM(N3:N14) -> 16497.91 | P17: =SUM(P3:P14) -> 9441.8 | Q17: =SUM(Q3:Q14) -> 19131.51 | R17: =SUM(R3:R14) -> 1634 | S17: =Q17+R17 -> 20765.51 | W17: =SUM(W3:W14) -> 6880.609
B18: 11000 | D18: 14500 | G18: Average | I18: kWh | J18: kWh | K18: kWh | L18: =AVERAGE(L3:L12) -> 2.703 | M18: =AVERAGE(M3:M12) -> 2.3 | N18: =N17/9 -> 1833.1011 | P18: kWh
A21: Total price for setup | B21: 155000
A22: Payback time | B22: =B21/S17 -> 7.4643002 | C22: år
A23: Projected yearly savings | B23: =S17+(2000)+(250*1) -> 23015.51
A24: Projected payback time | B24: =B21/B23 -> 6.734589 | C24: år
A26: Tilbagebetalingstid ved optimalt brug af setup | B26: =B21/(S17+W17) -> 5.6065736 | C26: år
A29: If we were able to use all electricity produced | B29: =(B17-G17)/10 -> 363.3 | C29: extra per month
A30: Monthly savings | B30: =B29*L18 -> 981.9999
A33: 28000
